sakmapper/__init__.py
sakmapper/lens.py
sakmapper/network.py
sakmapper-0.3.dist-info/DESCRIPTION.rst
sakmapper-0.3.dist-info/LICENSE.txt
sakmapper-0.3.dist-info/METADATA
sakmapper-0.3.dist-info/RECORD
sakmapper-0.3.dist-info/WHEEL
sakmapper-0.3.dist-info/metadata.json
sakmapper-0.3.dist-info/top_level.txt
