Metadata-Version: 2.0
Name: sakmapper
Version: 0.3
Summary: implementation of the mapper algorithm
Home-page: https://github.com/szairis/sakmapper
Author: sakellarios zairis
Author-email: szairis@gmail.com
License: MIT
Platform: UNKNOWN
Requires-Dist: networkx
Requires-Dist: numpy
Requires-Dist: pandas
Requires-Dist: scikit-learn
Requires-Dist: scipy
